Metadata-Version: 2.1
Name: rand-useragent
Version: 0.2.0
Summary: An up-to-date simple random user-agent with real world database.
Author-email: Tolulope Kuyoro <tolukuyoro@gmail.com>
License: BSD-3-Clause
Project-URL: homepage, https://github.com/redbugg/rand-useragent
Project-URL: source, https://github.com/redbugg/rand-useragent
Classifier: Development Status :: 5 - Production/Stable
Classifier: Intended Audience :: Developers
Classifier: License :: OSI Approved :: BSD License
Classifier: Programming Language :: Python
Classifier: Programming Language :: Python :: 3
Classifier: Programming Language :: Python :: 3 :: Only
Classifier: Operating System :: OS Independent
Classifier: Topic :: Internet :: WWW/HTTP
Classifier: Topic :: Software Development
Classifier: Topic :: Software Development :: Libraries :: Python Modules
Classifier: Topic :: Utilities
Requires-Python: >=3.7
Provides-Extra: dev
License-File: LICENSE
